h5dataframe/__init__.py
h5dataframe/_typing.py
h5dataframe/array_algos.py
h5dataframe/block.py
h5dataframe/categorical.py
h5dataframe/dataframe.py
h5dataframe/manager.py
h5dataframe/patch.py
h5dataframe/py.typed
h5dataframe-0.2.3.dist-info/WHEEL
h5dataframe-0.2.3.dist-info/METADATA
h5dataframe-0.2.3.dist-info/RECORD
