Metadata-Version: 2.4
Name: h5dataframe
Version: 0.2.3
Summary: Drop-in replacement for pandas DataFrames that allows to store data on an hdf5 file and manipulate data directly from that hdf5 file without loading it in memory.
Author: Matteo Bouvier
Author-email: Matteo Bouvier <matteo.bouvier@hotmail.fr>
License-Expression: CECILL-B
Requires-Dist: pandas>=2.2
Requires-Dist: ch5mpy>=0.5.1
Requires-Python: >=3.10
